annotatepy/__init__.py
annotatepy/annotate.py
annotatepy/console.py
annotatepy-0.3.0.dist-info/LICENSE
annotatepy-0.3.0.dist-info/METADATA
annotatepy-0.3.0.dist-info/WHEEL
annotatepy-0.3.0.dist-info/entry_points.txt
annotatepy-0.3.0.dist-info/top_level.txt
annotatepy-0.3.0.dist-info/RECORD
